bro/__init__.py
bro/__version__.py
bro/temp.py
bro_api-0.1.0rc2.dist-info/LICENSE
bro_api-0.1.0rc2.dist-info/METADATA
bro_api-0.1.0rc2.dist-info/WHEEL
bro_api-0.1.0rc2.dist-info/top_level.txt
bro_api-0.1.0rc2.dist-info/RECORD
