Metadata-Version: 2.1
Name: bro-api
Version: 0.1.0rc2
Summary: Open source python library for accessing BRO API
Home-page: https://github.com/viktor-platform/bro-api
Author: VIKTOR
Author-email: support@viktor.ai
License: MIT
License-File: LICENSE
